.gitignore
CMakeLists.txt
CONTRIBUTING.md
LICENSE
README.md
build.sh
clean_all.sh
pyproject.toml
setup.py
test.sh
.github/workflows/hanabi-publish.yml
.github/workflows/pylint.yml
.vscode/launch.json
Agents/__init__.py
Agents/htgs_info_agent.py
Agents/htgs_own_agent.py
Agents/htgs_rec_agent.py
INFO_Strategy/__init__.py
INFO_Strategy/color_enum.py
INFO_Strategy/possibility_table.py
examples/CMakeLists.txt
examples/README.md
examples/game_example.cc
examples/game_example.py
examples/rl_env_example.py
hanabi_learning_environment/CMakeLists.txt
hanabi_learning_environment/__init__.py
hanabi_learning_environment/pyhanabi.cc
hanabi_learning_environment/pyhanabi.h
hanabi_learning_environment/pyhanabi.py
hanabi_learning_environment/rl_env.py
hanabi_learning_environment/agents/__init__.py
hanabi_learning_environment/agents/random_agent.py
hanabi_learning_environment/agents/simple_agent.py
hanabi_learning_environment/agents/test_agent.py
hanabi_learning_environment/agents/rainbow/README.md
hanabi_learning_environment/agents/rainbow/dqn_agent.py
hanabi_learning_environment/agents/rainbow/prioritized_replay_memory.py
hanabi_learning_environment/agents/rainbow/rainbow_agent.py
hanabi_learning_environment/agents/rainbow/replay_memory.py
hanabi_learning_environment/agents/rainbow/run_experiment.py
hanabi_learning_environment/agents/rainbow/train.py
hanabi_learning_environment/agents/rainbow/configs/hanabi_rainbow.gin
hanabi_learning_environment/agents/rainbow/third_party/__init__.py
hanabi_learning_environment/agents/rainbow/third_party/dopamine/LICENSE
hanabi_learning_environment/agents/rainbow/third_party/dopamine/__init__.py
hanabi_learning_environment/agents/rainbow/third_party/dopamine/checkpointer.py
hanabi_learning_environment/agents/rainbow/third_party/dopamine/iteration_statistics.py
hanabi_learning_environment/agents/rainbow/third_party/dopamine/logger.py
hanabi_learning_environment/agents/rainbow/third_party/dopamine/sum_tree.py
ws2223_group7_hanabi_learning_environment_hgts.egg-info/PKG-INFO
ws2223_group7_hanabi_learning_environment_hgts.egg-info/SOURCES.txt
ws2223_group7_hanabi_learning_environment_hgts.egg-info/dependency_links.txt
ws2223_group7_hanabi_learning_environment_hgts.egg-info/entry_points.txt
ws2223_group7_hanabi_learning_environment_hgts.egg-info/requires.txt
ws2223_group7_hanabi_learning_environment_hgts.egg-info/top_level.txt